{
  "comebacks": [
    {
      "brand": "vuori",
      "url": "https://vuoriclothing.com/products/womens-villa-trouser-ink",
      "product_name": "villa trouser",
      "category": "other",
      "subcategory": "other",
      "gender": "womens",
      "first_seen": "2026-02-03T23:02:44.018447",
      "removed_at": "2026-02-12T02:05:04.631257",
      "returned_at": "2026-02-12T06:08:22.622881",
      "days_gone": 0
    },
    {
      "brand": "vuori",
      "url": "https://vuoriclothing.com/products/womens-elevation-ankle-trouser-black-heather",
      "product_name": "elevation ankle trouser",
      "category": "other",
      "subcategory": "other",
      "gender": "womens",
      "first_seen": "2026-02-03T23:02:44.019629",
      "removed_at": "2026-02-12T02:05:04.631257",
      "returned_at": "2026-02-12T06:08:22.622881",
      "days_gone": 0
    },
    {
      "brand": "vuori",
      "url": "https://vuoriclothing.com/products/womens-halo-straight-leg-trouser-cosmic-heather",
      "product_name": "halo straight leg trouser cosmic",
      "category": "other",
      "subcategory": "other",
      "gender": "womens",
      "first_seen": "2026-02-03T23:02:44.020094",
      "removed_at": "2026-02-12T02:05:04.631257",
      "returned_at": "2026-02-12T06:08:22.622881",
      "days_gone": 0
    },
    {
      "brand": "vuori",
      "url": "https://vuoriclothing.com/products/strato-tech-tee-dark-umber-heather",
      "product_name": "strato tech tee",
      "category": "tops",
      "subcategory": "tees",
      "gender": "mens",
      "first_seen": "2026-02-03T23:02:44.022114",
      "removed_at": "2026-02-12T02:05:04.631257",
      "returned_at": "2026-02-12T06:08:22.622881",
      "days_gone": 0
    },
    {
      "brand": "vuori",
      "url": "https://vuoriclothing.com/products/sunday-element-vest-kale-heather",
      "product_name": "sunday element vest",
      "category": "outerwear",
      "subcategory": "vests",
      "gender": "mens",
      "first_seen": "2026-02-03T23:02:44.022222",
      "removed_at": "2026-02-12T02:05:04.631257",
      "returned_at": "2026-02-12T06:08:22.622881",
      "days_gone": 0
    },
    {
      "brand": "vuori",
      "url": "https://vuoriclothing.com/products/sunday-performance-sweatpant-classic-28-grey-heather",
      "product_name": "sunday performance sweatpant classic 28",
      "category": "bottoms",
      "subcategory": "sweatpants",
      "gender": "mens",
      "first_seen": "2026-02-03T23:02:44.022287",
      "removed_at": "2026-02-12T02:05:04.631257",
      "returned_at": "2026-02-12T06:08:22.622881",
      "days_gone": 0
    },
    {
      "brand": "vuori",
      "url": "https://vuoriclothing.com/products/strato-muscle-tee-pool-blue-heather",
      "product_name": "strato muscle tee pool",
      "category": "tops",
      "subcategory": "tees",
      "gender": "mens",
      "first_seen": "2026-02-03T23:02:44.024477",
      "removed_at": "2026-02-12T02:05:04.631257",
      "returned_at": "2026-02-12T06:08:22.622881",
      "days_gone": 0
    },
    {
      "brand": "vuori",
      "url": "https://vuoriclothing.com/products/short-sleeve-strato-pocket-tee-relaxed-fit-chambray-heather",
      "product_name": "short sleeve strato pocket tee relaxed fit",
      "category": "bottoms",
      "subcategory": "other",
      "gender": "mens",
      "first_seen": "2026-02-03T23:02:44.024636",
      "removed_at": "2026-02-12T02:05:04.631257",
      "returned_at": "2026-02-12T06:08:22.622881",
      "days_gone": 0
    },
    {
      "brand": "vuori",
      "url": "https://vuoriclothing.com/products/long-sleeve-ponto-performance-tee-misty-blue-heather",
      "product_name": "long sleeve ponto performance tee misty",
      "category": "tops",
      "subcategory": "tees",
      "gender": "mens",
      "first_seen": "2026-02-03T23:02:44.024761",
      "removed_at": "2026-02-12T02:05:04.631257",
      "returned_at": "2026-02-12T06:08:22.622881",
      "days_gone": 0
    },
    {
      "brand": "vuori",
      "url": "https://vuoriclothing.com/products/ace-polo-agate-green",
      "product_name": "ace polo agate",
      "category": "tops",
      "subcategory": "polos",
      "gender": "mens",
      "first_seen": "2026-02-03T23:02:44.025440",
      "removed_at": "2026-02-12T02:05:04.631257",
      "returned_at": "2026-02-12T06:08:22.622881",
      "days_gone": 0
    },
    {
      "brand": "vuori",
      "url": "https://vuoriclothing.com/products/seaside-shirt-jacket-salt",
      "product_name": "seaside shirt jacket",
      "category": "tops",
      "subcategory": "other",
      "gender": "unisex",
      "first_seen": "2026-02-03T23:02:44.025792",
      "removed_at": "2026-02-12T02:05:04.631257",
      "returned_at": "2026-02-12T06:08:22.622881",
      "days_gone": 0
    },
    {
      "brand": "vuori",
      "url": "https://vuoriclothing.com/products/coronado-pullover-hoodie-2-0-light-heather-grey",
      "product_name": "coronado pullover hoodie 2 0 light",
      "category": "outerwear",
      "subcategory": "hoodies",
      "gender": "mens",
      "first_seen": "2026-02-03T23:02:44.025813",
      "removed_at": "2026-02-12T02:05:04.631257",
      "returned_at": "2026-02-12T06:08:22.622881",
      "days_gone": 0
    },
    {
      "brand": "vuori",
      "url": "https://vuoriclothing.com/products/sunday-hoodie-2-0-agate-green-heather",
      "product_name": "sunday hoodie 2 0 agate",
      "category": "outerwear",
      "subcategory": "hoodies",
      "gender": "mens",
      "first_seen": "2026-02-03T23:02:44.025845",
      "removed_at": "2026-02-12T02:05:04.631257",
      "returned_at": "2026-02-12T06:08:22.622881",
      "days_gone": 0
    },
    {
      "brand": "vuori",
      "url": "https://vuoriclothing.com/products/kore-unlined-short-toast",
      "product_name": "kore unlined short",
      "category": "bottoms",
      "subcategory": "shorts",
      "gender": "mens",
      "first_seen": "2026-02-03T23:02:44.027659",
      "removed_at": "2026-02-12T02:05:04.631257",
      "returned_at": "2026-02-12T06:08:22.622881",
      "days_gone": 0
    },
    {
      "brand": "vuori",
      "url": "https://vuoriclothing.com/products/seaside-straight-leg-sweatpant-30-salt",
      "product_name": "seaside straight leg sweatpant 30",
      "category": "bottoms",
      "subcategory": "sweatpants",
      "gender": "unisex",
      "first_seen": "2026-02-03T23:02:44.028745",
      "removed_at": "2026-02-12T02:05:04.631257",
      "returned_at": "2026-02-12T06:08:22.622881",
      "days_gone": 0
    },
    {
      "brand": "vuori",
      "url": "https://vuoriclothing.com/products/v1-logo-tee-espresso-heather",
      "product_name": "v1 logo tee",
      "category": "tops",
      "subcategory": "tees",
      "gender": "unisex",
      "first_seen": "2026-02-03T23:02:44.030255",
      "removed_at": "2026-02-12T02:05:04.631257",
      "returned_at": "2026-02-12T06:08:22.622881",
      "days_gone": 0
    },
    {
      "brand": "vuori",
      "url": "https://vuoriclothing.com/products/womens-performance-jogger-long-huckleberry-heather",
      "product_name": "performance jogger long huckleberry",
      "category": "bottoms",
      "subcategory": "joggers",
      "gender": "womens",
      "first_seen": "2026-02-03T23:02:44.031794",
      "removed_at": "2026-02-12T02:05:04.631257",
      "returned_at": "2026-02-12T06:08:22.622881",
      "days_gone": 0
    },
    {
      "brand": "vuori",
      "url": "https://vuoriclothing.com/products/womens-vuori-allthefeels-legging-blue-coast",
      "product_name": "vuori allthefeels legging coast",
      "category": "bottoms",
      "subcategory": "leggings",
      "gender": "womens",
      "first_seen": "2026-02-03T23:02:44.032153",
      "removed_at": "2026-02-12T02:05:04.631257",
      "returned_at": "2026-02-12T06:08:22.622881",
      "days_gone": 0
    },
    {
      "brand": "vuori",
      "url": "https://vuoriclothing.com/products/womens-villa-sport-trouser-pant-ink",
      "product_name": "villa sport trouser pant",
      "category": "bottoms",
      "subcategory": "pants",
      "gender": "womens",
      "first_seen": "2026-02-03T23:02:44.032608",
      "removed_at": "2026-02-12T02:05:04.631257",
      "returned_at": "2026-02-12T06:08:22.622881",
      "days_gone": 0
    },
    {
      "brand": "vuori",
      "url": "https://vuoriclothing.com/products/womens-villa-sport-trouser-pant-viridian",
      "product_name": "villa sport trouser pant viridian",
      "category": "bottoms",
      "subcategory": "pants",
      "gender": "womens",
      "first_seen": "2026-02-03T23:02:44.032619",
      "removed_at": "2026-02-12T02:05:04.631257",
      "returned_at": "2026-02-12T06:08:22.622881",
      "days_gone": 0
    },
    {
      "brand": "vuori",
      "url": "https://vuoriclothing.com/products/womens-daily-pocket-legging-light-french-blue",
      "product_name": "daily pocket legging light french",
      "category": "bottoms",
      "subcategory": "leggings",
      "gender": "womens",
      "first_seen": "2026-02-03T23:02:44.033749",
      "removed_at": "2026-02-12T02:05:04.631257",
      "returned_at": "2026-02-12T06:08:22.622881",
      "days_gone": 0
    },
    {
      "brand": "vuori",
      "url": "https://vuoriclothing.com/products/long-sleeve-strato-tech-tee-isle-blue-heather",
      "product_name": "long sleeve strato tech tee isle",
      "category": "tops",
      "subcategory": "tees",
      "gender": "mens",
      "first_seen": "2026-02-03T23:02:44.035507",
      "removed_at": "2026-02-12T02:05:04.631257",
      "returned_at": "2026-02-12T06:08:22.622881",
      "days_gone": 0
    },
    {
      "brand": "vuori",
      "url": "https://vuoriclothing.com/products/womens-short-sleeve-seamless-surge-tee-soft-sky",
      "product_name": "short sleeve seamless surge tee",
      "category": "bottoms",
      "subcategory": "other",
      "gender": "womens",
      "first_seen": "2026-02-03T23:02:44.038061",
      "removed_at": "2026-02-12T02:05:04.631257",
      "returned_at": "2026-02-12T06:08:22.622881",
      "days_gone": 0
    },
    {
      "brand": "vuori",
      "url": "https://vuoriclothing.com/products/womens-daydream-crew-agate-green-heather",
      "product_name": "daydream crew agate",
      "category": "other",
      "subcategory": "other",
      "gender": "womens",
      "first_seen": "2026-02-03T23:02:44.038445",
      "removed_at": "2026-02-12T02:05:04.631257",
      "returned_at": "2026-02-12T06:08:22.622881",
      "days_gone": 0
    },
    {
      "brand": "vuori",
      "url": "https://vuoriclothing.com/products/womens-long-sleeve-tuvalu-boat-neck-black",
      "product_name": "long sleeve tuvalu boat neck",
      "category": "other",
      "subcategory": "other",
      "gender": "womens",
      "first_seen": "2026-02-03T23:02:44.038673",
      "removed_at": "2026-02-12T02:05:04.631257",
      "returned_at": "2026-02-12T06:08:22.622881",
      "days_gone": 0
    },
    {
      "brand": "vuori",
      "url": "https://vuoriclothing.com/products/womens-restore-oversized-hoodie-agate-green",
      "product_name": "restore oversized hoodie agate",
      "category": "outerwear",
      "subcategory": "hoodies",
      "gender": "womens",
      "first_seen": "2026-02-03T23:02:44.038781",
      "removed_at": "2026-02-12T02:05:04.631257",
      "returned_at": "2026-02-12T06:08:22.622881",
      "days_gone": 0
    },
    {
      "brand": "vuori",
      "url": "https://vuoriclothing.com/products/womens-waffle-full-zip-hoodie-soft-sky",
      "product_name": "waffle full zip hoodie",
      "category": "outerwear",
      "subcategory": "hoodies",
      "gender": "womens",
      "first_seen": "2026-02-03T23:02:44.038996",
      "removed_at": "2026-02-12T02:05:04.631257",
      "returned_at": "2026-02-12T06:08:22.622881",
      "days_gone": 0
    },
    {
      "brand": "vuori",
      "url": "https://vuoriclothing.com/products/womens-restore-shrug-washed-black",
      "product_name": "restore shrug",
      "category": "other",
      "subcategory": "other",
      "gender": "womens",
      "first_seen": "2026-02-03T23:02:44.039061",
      "removed_at": "2026-02-12T02:05:04.631257",
      "returned_at": "2026-02-12T06:08:22.622881",
      "days_gone": 0
    },
    {
      "brand": "vuori",
      "url": "https://vuoriclothing.com/products/womens-vuori-alltheform-fitness-jacket-blue-coast",
      "product_name": "vuori alltheform fitness jacket coast",
      "category": "outerwear",
      "subcategory": "jackets",
      "gender": "womens",
      "first_seen": "2026-02-03T23:02:44.039894",
      "removed_at": "2026-02-12T02:05:04.631257",
      "returned_at": "2026-02-12T06:08:22.622881",
      "days_gone": 0
    },
    {
      "brand": "vuori",
      "url": "https://vuoriclothing.com/products/waffle-henley-bone",
      "product_name": "waffle henley",
      "category": "tops",
      "subcategory": "other",
      "gender": "mens",
      "first_seen": "2026-02-05T01:11:44.335919",
      "removed_at": "2026-02-12T02:05:04.631257",
      "returned_at": "2026-02-12T06:08:22.622881",
      "days_gone": 0
    },
    {
      "brand": "vuori",
      "url": "https://vuoriclothing.com/products/womens-performance-jogger-chia-heather",
      "product_name": "performance jogger chia",
      "category": "bottoms",
      "subcategory": "joggers",
      "gender": "womens",
      "first_seen": "2026-02-05T01:11:44.338733",
      "removed_at": "2026-02-12T02:05:04.631257",
      "returned_at": "2026-02-12T06:08:22.622881",
      "days_gone": 0
    },
    {
      "brand": "vuori",
      "url": "https://vuoriclothing.com/products/seaside-pant-30-spiced-apple",
      "product_name": "seaside pant 30 spiced apple",
      "category": "bottoms",
      "subcategory": "pants",
      "gender": "unisex",
      "first_seen": "2026-02-05T01:11:44.340540",
      "removed_at": "2026-02-12T02:05:04.631257",
      "returned_at": "2026-02-12T06:08:22.622881",
      "days_gone": 0
    },
    {
      "brand": "vuori",
      "url": "https://vuoriclothing.com/products/v1-vuori-wordmark-logo-tee-white",
      "product_name": "v1 vuori wordmark logo tee",
      "category": "tops",
      "subcategory": "tees",
      "gender": "unisex",
      "first_seen": "2026-02-05T01:11:44.341027",
      "removed_at": "2026-02-12T02:05:04.631257",
      "returned_at": "2026-02-12T06:08:22.622881",
      "days_gone": 0
    },
    {
      "brand": "vuori",
      "url": "https://vuoriclothing.com/products/womens-cove-boyfriend-tank-black",
      "product_name": "cove boyfriend tank",
      "category": "tops",
      "subcategory": "tanks",
      "gender": "womens",
      "first_seen": "2026-02-05T01:11:44.341142",
      "removed_at": "2026-02-12T02:05:04.631257",
      "returned_at": "2026-02-12T06:08:22.622881",
      "days_gone": 0
    },
    {
      "brand": "vuori",
      "url": "https://vuoriclothing.com/products/banks-short-black-camo",
      "product_name": "banks short black",
      "category": "bottoms",
      "subcategory": "shorts",
      "gender": "mens",
      "first_seen": "2026-02-05T05:12:40.450342",
      "removed_at": "2026-02-12T02:05:04.631257",
      "returned_at": "2026-02-12T06:08:22.622881",
      "days_gone": 0
    },
    {
      "brand": "vuori",
      "url": "https://vuoriclothing.com/products/womens-canyon-insulated-jacket-bone",
      "product_name": "canyon insulated jacket",
      "category": "outerwear",
      "subcategory": "jackets",
      "gender": "womens",
      "first_seen": "2026-02-05T05:12:40.451428",
      "removed_at": "2026-02-12T02:05:04.631257",
      "returned_at": "2026-02-12T06:08:22.622881",
      "days_gone": 0
    },
    {
      "brand": "vuori",
      "url": "https://vuoriclothing.com/products/womens-halo-cardigan-2-0-ecru-heather",
      "product_name": "halo cardigan 2 0",
      "category": "other",
      "subcategory": "other",
      "gender": "womens",
      "first_seen": "2026-02-05T05:12:40.454366",
      "removed_at": "2026-02-12T02:05:04.631257",
      "returned_at": "2026-02-12T06:08:22.622881",
      "days_gone": 0
    },
    {
      "brand": "vuori",
      "url": "https://vuoriclothing.com/products/strato-tech-tee-multipack-multi",
      "product_name": "strato tech tee multipack",
      "category": "tops",
      "subcategory": "tees",
      "gender": "mens",
      "first_seen": "2026-02-05T05:12:40.454786",
      "removed_at": "2026-02-12T02:05:04.631257",
      "returned_at": "2026-02-12T06:08:22.622881",
      "days_gone": 0
    },
    {
      "brand": "vuori",
      "url": "https://vuoriclothing.com/products/womens-alps-boyfriend-cardigan-marshmallow",
      "product_name": "alps boyfriend cardigan marshmallow",
      "category": "other",
      "subcategory": "other",
      "gender": "womens",
      "first_seen": "2026-02-05T05:12:40.456636",
      "removed_at": "2026-02-12T02:05:04.631257",
      "returned_at": "2026-02-12T06:08:22.622881",
      "days_gone": 0
    },
    {
      "brand": "vuori",
      "url": "https://vuoriclothing.com/products/womens-pose-plyo-tank-mist",
      "product_name": "pose plyo tank mist",
      "category": "tops",
      "subcategory": "tanks",
      "gender": "womens",
      "first_seen": "2026-02-06T07:56:44.914972",
      "removed_at": "2026-02-12T02:05:04.631257",
      "returned_at": "2026-02-12T06:08:22.622881",
      "days_gone": 0
    },
    {
      "brand": "vuori",
      "url": "https://vuoriclothing.com/products/bering-down-parka-black",
      "product_name": "bering down parka",
      "category": "outerwear",
      "subcategory": "other",
      "gender": "unisex",
      "first_seen": "2026-02-06T07:56:44.917576",
      "removed_at": "2026-02-12T02:05:04.631257",
      "returned_at": "2026-02-12T06:08:22.622881",
      "days_gone": 0
    },
    {
      "brand": "vuori",
      "url": "https://vuoriclothing.com/products/womens-long-sleeve-halo-essential-scoop-chia-heather",
      "product_name": "long sleeve halo essential scoop chia",
      "category": "other",
      "subcategory": "other",
      "gender": "womens",
      "first_seen": "2026-02-06T07:56:44.917905",
      "removed_at": "2026-02-12T02:05:04.631257",
      "returned_at": "2026-02-12T06:08:22.622881",
      "days_gone": 0
    },
    {
      "brand": "vuori",
      "url": "https://vuoriclothing.com/products/womens-alps-boyfriend-cardigan-black",
      "product_name": "alps boyfriend cardigan",
      "category": "other",
      "subcategory": "other",
      "gender": "womens",
      "first_seen": "2026-02-06T07:56:44.918217",
      "removed_at": "2026-02-12T02:05:04.631257",
      "returned_at": "2026-02-12T06:08:22.622881",
      "days_gone": 0
    },
    {
      "brand": "vuori",
      "url": "https://vuoriclothing.com/products/womens-lund-insulated-jacket-dark-azure",
      "product_name": "lund insulated jacket",
      "category": "outerwear",
      "subcategory": "jackets",
      "gender": "womens",
      "first_seen": "2026-02-06T07:56:44.920946",
      "removed_at": "2026-02-12T02:05:04.631257",
      "returned_at": "2026-02-12T06:08:22.622881",
      "days_gone": 0
    },
    {
      "brand": "vuori",
      "url": "https://vuoriclothing.com/products/waffle-crew-bone",
      "product_name": "waffle crew",
      "category": "other",
      "subcategory": "other",
      "gender": "mens",
      "first_seen": "2026-02-07T08:00:35.790991",
      "removed_at": "2026-02-12T02:05:04.631257",
      "returned_at": "2026-02-12T06:08:22.622881",
      "days_gone": 0
    },
    {
      "brand": "vuori",
      "url": "https://vuoriclothing.com/products/womens-short-sleeve-pose-button-up-white-heather-grey",
      "product_name": "short sleeve pose button up white",
      "category": "bottoms",
      "subcategory": "other",
      "gender": "womens",
      "first_seen": "2026-02-07T08:00:35.795813",
      "removed_at": "2026-02-12T02:05:04.631257",
      "returned_at": "2026-02-12T06:08:22.622881",
      "days_gone": 0
    },
    {
      "brand": "vuori",
      "url": "https://vuoriclothing.com/products/womens-long-sleeve-halo-snap-cardigan-evergreen-heather",
      "product_name": "long sleeve halo snap cardigan evergreen",
      "category": "other",
      "subcategory": "other",
      "gender": "womens",
      "first_seen": "2026-02-07T08:00:35.795845",
      "removed_at": "2026-02-12T02:05:04.631257",
      "returned_at": "2026-02-12T06:08:22.622881",
      "days_gone": 0
    },
    {
      "brand": "vuori",
      "url": "https://vuoriclothing.com/products/womens-halo-modern-pullover-hoodie-magenta-heather",
      "product_name": "halo modern pullover hoodie",
      "category": "outerwear",
      "subcategory": "hoodies",
      "gender": "womens",
      "first_seen": "2026-02-07T08:00:35.795893",
      "removed_at": "2026-02-12T02:05:04.631257",
      "returned_at": "2026-02-12T06:08:22.622881",
      "days_gone": 0
    },
    {
      "brand": "vuori",
      "url": "https://vuoriclothing.com/products/womens-villa-vibes-wideleg-short-espresso",
      "product_name": "villa vibes wideleg short",
      "category": "bottoms",
      "subcategory": "shorts",
      "gender": "womens",
      "first_seen": "2026-02-07T08:00:35.796723",
      "removed_at": "2026-02-12T02:05:04.631257",
      "returned_at": "2026-02-12T06:08:22.622881",
      "days_gone": 0
    },
    {
      "brand": "vuori",
      "url": "https://vuoriclothing.com/products/benton-stretch-twill-pant-classic-fit-32-peppercorn",
      "product_name": "benton stretch twill pant classic fit 32 peppercorn",
      "category": "bottoms",
      "subcategory": "pants",
      "gender": "mens",
      "first_seen": "2026-02-07T08:00:35.797905",
      "removed_at": "2026-02-12T02:05:04.631257",
      "returned_at": "2026-02-12T06:08:22.622881",
      "days_gone": 0
    },
    {
      "brand": "vuori",
      "url": "https://vuoriclothing.com/products/womens-long-sleeve-tuvalu-boat-neck-bone",
      "product_name": "long sleeve tuvalu boat neck",
      "category": "other",
      "subcategory": "other",
      "gender": "womens",
      "first_seen": "2026-02-07T08:00:35.798452",
      "removed_at": "2026-02-12T02:05:04.631257",
      "returned_at": "2026-02-12T06:08:22.622881",
      "days_gone": 0
    },
    {
      "brand": "vuori",
      "url": "https://vuoriclothing.com/products/womens-long-sleeve-halo-essential-scoop-raisin",
      "product_name": "long sleeve halo essential scoop",
      "category": "other",
      "subcategory": "other",
      "gender": "womens",
      "first_seen": "2026-02-08T04:00:36.499304",
      "removed_at": "2026-02-12T02:05:04.631257",
      "returned_at": "2026-02-12T06:08:22.622881",
      "days_gone": 0
    },
    {
      "brand": "vuori",
      "url": "https://vuoriclothing.com/products/womens-restore-oversized-hoodie-huckleberry",
      "product_name": "restore oversized hoodie huckleberry",
      "category": "outerwear",
      "subcategory": "hoodies",
      "gender": "womens",
      "first_seen": "2026-02-08T04:00:36.499589",
      "removed_at": "2026-02-12T02:05:04.631257",
      "returned_at": "2026-02-12T06:08:22.622881",
      "days_gone": 0
    },
    {
      "brand": "vuori",
      "url": "https://vuoriclothing.com/products/womens-vuori-allthefeels-legging-evergreen",
      "product_name": "vuori allthefeels legging evergreen",
      "category": "bottoms",
      "subcategory": "leggings",
      "gender": "womens",
      "first_seen": "2026-02-08T04:00:36.500042",
      "removed_at": "2026-02-12T02:05:04.631257",
      "returned_at": "2026-02-12T06:08:22.622881",
      "days_gone": 0
    },
    {
      "brand": "vuori",
      "url": "https://vuoriclothing.com/products/womens-villa-pinstripe-trouser-pant-s-navy-pinstripe",
      "product_name": "villa pinstripe trouser pant s pinstripe",
      "category": "bottoms",
      "subcategory": "pants",
      "gender": "womens",
      "first_seen": "2026-02-08T04:00:36.500325",
      "removed_at": "2026-02-12T02:05:04.631257",
      "returned_at": "2026-02-12T06:08:22.622881",
      "days_gone": 0
    },
    {
      "brand": "vuori",
      "url": "https://vuoriclothing.com/products/womens-emilie-cashmere-crew-cherry",
      "product_name": "emilie cashmere crew",
      "category": "other",
      "subcategory": "other",
      "gender": "womens",
      "first_seen": "2026-02-10T04:11:08.537094",
      "removed_at": "2026-02-12T02:05:04.631257",
      "returned_at": "2026-02-12T06:08:22.622881",
      "days_gone": 0
    },
    {
      "brand": "vuori",
      "url": "https://vuoriclothing.com/products/womens-vuori-allthefeels-corset-legging-blue-coast",
      "product_name": "vuori allthefeels corset legging coast",
      "category": "bottoms",
      "subcategory": "leggings",
      "gender": "womens",
      "first_seen": "2026-02-10T04:11:08.537787",
      "removed_at": "2026-02-12T02:05:04.631257",
      "returned_at": "2026-02-12T06:08:22.622881",
      "days_gone": 0
    },
    {
      "brand": "vuori",
      "url": "https://vuoriclothing.com/products/womens-emilie-cashmere-oversized-v-neck-ocean-blue",
      "product_name": "emilie cashmere oversized v neck ocean",
      "category": "other",
      "subcategory": "other",
      "gender": "womens",
      "first_seen": "2026-02-10T04:11:08.539630",
      "removed_at": "2026-02-12T02:05:04.631257",
      "returned_at": "2026-02-12T06:08:22.622881",
      "days_gone": 0
    },
    {
      "brand": "alo",
      "url": "https://www.aloyoga.com/products/m3109r-the-triumph-hoodie-grey-triblend-womans",
      "product_name": "m3109r the triumph hoodie triblend womans",
      "category": "outerwear",
      "subcategory": "hoodies",
      "gender": "mens",
      "first_seen": "2026-02-03T23:12:32.614254",
      "removed_at": "2026-02-12T02:05:04.631257",
      "returned_at": "2026-02-12T06:08:22.622881",
      "days_gone": 0
    },
    {
      "brand": "alo",
      "url": "https://www.aloyoga.com/products/w8306p-airlift-winter-warm-ski-time-bib-black",
      "product_name": "w8306p airlift winter warm ski time bib",
      "category": "other",
      "subcategory": "other",
      "gender": "womens",
      "first_seen": "2026-02-03T23:12:32.621380",
      "removed_at": "2026-02-12T02:05:04.631257",
      "returned_at": "2026-02-12T06:08:22.622881",
      "days_gone": 0
    },
    {
      "brand": "alo",
      "url": "https://www.aloyoga.com/products/a0411w-womens-strappy-siren-grip-sock-smoky-quartz",
      "product_name": "a0411w womens strappy siren grip sock smoky quartz",
      "category": "accessories",
      "subcategory": "socks",
      "gender": "womens",
      "first_seen": "2026-02-03T23:12:32.626845",
      "removed_at": "2026-02-12T02:05:04.631257",
      "returned_at": "2026-02-12T06:08:22.622881",
      "days_gone": 0
    },
    {
      "brand": "alo",
      "url": "https://www.aloyoga.com/products/w8291r-micro-plisse-game-on-tennis-dress-pink-quartz",
      "product_name": "w8291r micro plisse game on tennis dress quartz",
      "category": "dresses",
      "subcategory": "tennis_dress",
      "gender": "womens",
      "first_seen": "2026-02-03T23:12:32.629737",
      "removed_at": "2026-02-12T02:05:04.631257",
      "returned_at": "2026-02-12T06:08:22.622881",
      "days_gone": 0
    },
    {
      "brand": "alo",
      "url": "https://www.aloyoga.com/products/w3859r-sweet-escape-zip-up-hoodie-taupe",
      "product_name": "w3859r sweet escape zip up hoodie",
      "category": "outerwear",
      "subcategory": "hoodies",
      "gender": "womens",
      "first_seen": "2026-02-03T23:12:32.631942",
      "removed_at": "2026-02-12T02:05:04.631257",
      "returned_at": "2026-02-12T06:08:22.622881",
      "days_gone": 0
    },
    {
      "brand": "alo",
      "url": "https://www.aloyoga.com/products/m1205r-conquer-reform-crewneck-short-sleeve-burgundy",
      "product_name": "m1205r conquer reform crewneck short sleeve",
      "category": "bottoms",
      "subcategory": "other",
      "gender": "mens",
      "first_seen": "2026-02-03T23:12:32.634661",
      "removed_at": "2026-02-12T02:05:04.631257",
      "returned_at": "2026-02-12T06:08:22.622881",
      "days_gone": 0
    },
    {
      "brand": "alo",
      "url": "https://www.aloyoga.com/products/w2704r-alo-softsculpt-tank-white",
      "product_name": "w2704r alo softsculpt tank",
      "category": "tops",
      "subcategory": "tanks",
      "gender": "womens",
      "first_seen": "2026-02-03T23:12:32.635634",
      "removed_at": "2026-02-12T02:05:04.631257",
      "returned_at": "2026-02-12T06:08:22.622881",
      "days_gone": 0
    },
    {
      "brand": "alo",
      "url": "https://www.aloyoga.com/products/w3295r-soho-pullover-bluestone",
      "product_name": "w3295r soho pullover bluestone",
      "category": "outerwear",
      "subcategory": "pullovers",
      "gender": "womens",
      "first_seen": "2026-02-03T23:12:32.635757",
      "removed_at": "2026-02-12T02:05:04.631257",
      "returned_at": "2026-02-12T06:08:22.622881",
      "days_gone": 0
    },
    {
      "brand": "alo",
      "url": "https://www.aloyoga.com/products/w3845r-hazy-mock-neck-pullover-burgundy",
      "product_name": "w3845r hazy mock neck pullover",
      "category": "outerwear",
      "subcategory": "pullovers",
      "gender": "womens",
      "first_seen": "2026-02-03T23:12:32.635799",
      "removed_at": "2026-02-12T02:05:04.631257",
      "returned_at": "2026-02-12T06:08:22.622881",
      "days_gone": 0
    },
    {
      "brand": "alo",
      "url": "https://www.aloyoga.com/products/w3924rg-cropped-accolade-crewneck-pink-wild-rose",
      "product_name": "w3924rg cropped accolade crewneck pink wild",
      "category": "tops",
      "subcategory": "crop_tops",
      "gender": "unisex",
      "first_seen": "2026-02-03T23:12:32.635935",
      "removed_at": "2026-02-12T02:05:04.631257",
      "returned_at": "2026-02-12T06:08:22.622881",
      "days_gone": 0
    },
    {
      "brand": "alo",
      "url": "https://www.aloyoga.com/products/w3950r-muse-crew-neck-pullover-black",
      "product_name": "w3950r muse crew neck pullover",
      "category": "outerwear",
      "subcategory": "pullovers",
      "gender": "womens",
      "first_seen": "2026-02-03T23:12:32.635987",
      "removed_at": "2026-02-12T02:05:04.631257",
      "returned_at": "2026-02-12T06:08:22.622881",
      "days_gone": 0
    },
    {
      "brand": "alo",
      "url": "https://www.aloyoga.com/products/w54260r-pinstripe-daylight-boxer-pant-regular-lunar-grey-white",
      "product_name": "w54260r pinstripe daylight boxer pant regular lunar grey",
      "category": "bottoms",
      "subcategory": "pants",
      "gender": "mens",
      "first_seen": "2026-02-03T23:12:32.636899",
      "removed_at": "2026-02-12T02:05:04.631257",
      "returned_at": "2026-02-12T06:08:22.622881",
      "days_gone": 0
    },
    {
      "brand": "alo",
      "url": "https://www.aloyoga.com/products/w51298r-airbrush-high-waist-heart-throb-legging-winter-frost-white",
      "product_name": "w51298r airbrush high waist heart throb legging winter frost",
      "category": "bottoms",
      "subcategory": "leggings",
      "gender": "womens",
      "first_seen": "2026-02-03T23:12:32.640226",
      "removed_at": "2026-02-12T02:05:04.631257",
      "returned_at": "2026-02-12T06:08:22.622881",
      "days_gone": 0
    },
    {
      "brand": "alo",
      "url": "https://www.aloyoga.com/products/w51154r-airlift-high-waist-7-8-line-up-legging-brownstone",
      "product_name": "w51154r airlift high waist 7 8 line up legging brownstone",
      "category": "bottoms",
      "subcategory": "leggings",
      "gender": "womens",
      "first_seen": "2026-02-03T23:12:32.640600",
      "removed_at": "2026-02-12T02:05:04.631257",
      "returned_at": "2026-02-12T06:08:22.622881",
      "days_gone": 0
    },
    {
      "brand": "alo",
      "url": "https://www.aloyoga.com/products/w31007r-polar-fleece-retreat-cover-up-white-heather-grey",
      "product_name": "w31007r polar fleece retreat cover up white",
      "category": "outerwear",
      "subcategory": "fleece",
      "gender": "unisex",
      "first_seen": "2026-02-03T23:12:32.642546",
      "removed_at": "2026-02-12T02:05:04.631257",
      "returned_at": "2026-02-12T06:08:22.622881",
      "days_gone": 0
    },
    {
      "brand": "alo",
      "url": "https://www.aloyoga.com/products/a0054u-airlift-headband-brownstone",
      "product_name": "a0054u airlift headband brownstone",
      "category": "accessories",
      "subcategory": "headwear",
      "gender": "unisex",
      "first_seen": "2026-02-03T23:12:32.644484",
      "removed_at": "2026-02-12T02:05:04.631257",
      "returned_at": "2026-02-12T06:08:22.622881",
      "days_gone": 0
    },
    {
      "brand": "alo",
      "url": "https://www.aloyoga.com/products/u3040rg-accolade-1-4-zip-pullover-winter-frost",
      "product_name": "u3040rg accolade 1 4 zip pullover winter frost",
      "category": "outerwear",
      "subcategory": "pullovers",
      "gender": "unisex",
      "first_seen": "2026-02-03T23:12:32.645037",
      "removed_at": "2026-02-12T02:05:04.631257",
      "returned_at": "2026-02-12T06:08:22.622881",
      "days_gone": 0
    },
    {
      "brand": "alo",
      "url": "https://www.aloyoga.com/products/u3040rg-accolade-1-4-zip-pullover-winter-frost-mens",
      "product_name": "u3040rg accolade 1 4 zip pullover winter frost mens",
      "category": "outerwear",
      "subcategory": "pullovers",
      "gender": "mens",
      "first_seen": "2026-02-03T23:12:32.645172",
      "removed_at": "2026-02-12T02:05:04.631257",
      "returned_at": "2026-02-12T06:08:22.622881",
      "days_gone": 0
    },
    {
      "brand": "alo",
      "url": "https://www.aloyoga.com/products/w2753r-ribbed-sea-coast-cropped-turtleneck-tank-black",
      "product_name": "w2753r ribbed sea coast cropped turtleneck tank",
      "category": "tops",
      "subcategory": "tanks",
      "gender": "womens",
      "first_seen": "2026-02-05T01:11:46.710744",
      "removed_at": "2026-02-12T02:05:04.631257",
      "returned_at": "2026-02-12T06:08:22.622881",
      "days_gone": 0
    },
    {
      "brand": "alo",
      "url": "https://www.aloyoga.com/products/w3858r-denim-knit-shawl-bold-red-dark-bold-red",
      "product_name": "w3858r denim knit shawl bold dark bold",
      "category": "other",
      "subcategory": "other",
      "gender": "womens",
      "first_seen": "2026-02-05T01:11:46.711972",
      "removed_at": "2026-02-12T02:05:04.631257",
      "returned_at": "2026-02-12T06:08:22.622881",
      "days_gone": 0
    },
    {
      "brand": "alo",
      "url": "https://www.aloyoga.com/products/w3845r-hazy-mock-neck-pullover-light-athletic-heather-grey",
      "product_name": "w3845r hazy mock neck pullover light athletic",
      "category": "outerwear",
      "subcategory": "pullovers",
      "gender": "womens",
      "first_seen": "2026-02-05T01:11:46.714986",
      "removed_at": "2026-02-12T02:05:04.631257",
      "returned_at": "2026-02-12T06:08:22.622881",
      "days_gone": 0
    },
    {
      "brand": "alo",
      "url": "https://www.aloyoga.com/products/w3438r-muse-hoodie-burgundy-truffle",
      "product_name": "w3438r muse hoodie truffle",
      "category": "outerwear",
      "subcategory": "hoodies",
      "gender": "womens",
      "first_seen": "2026-02-05T05:12:42.621616",
      "removed_at": "2026-02-12T02:05:04.631257",
      "returned_at": "2026-02-12T06:08:22.622881",
      "days_gone": 0
    },
    {
      "brand": "alo",
      "url": "https://www.aloyoga.com/products/u3032rg-accolade-hoodie-charcoal-green",
      "product_name": "u3032rg accolade hoodie charcoal",
      "category": "outerwear",
      "subcategory": "hoodies",
      "gender": "unisex",
      "first_seen": "2026-02-05T05:12:42.623293",
      "removed_at": "2026-02-12T02:05:04.631257",
      "returned_at": "2026-02-12T06:08:22.622881",
      "days_gone": 0
    },
    {
      "brand": "alo",
      "url": "https://www.aloyoga.com/products/w2737r-goddess-ribbed-go-to-tank-smoky-quartz",
      "product_name": "w2737r goddess ribbed go to tank smoky quartz",
      "category": "tops",
      "subcategory": "tanks",
      "gender": "womens",
      "first_seen": "2026-02-05T05:12:42.623414",
      "removed_at": "2026-02-12T02:05:04.631257",
      "returned_at": "2026-02-12T06:08:22.622881",
      "days_gone": 0
    },
    {
      "brand": "alo",
      "url": "https://www.aloyoga.com/products/u3032rg-accolade-hoodie-charcoal-green-mens",
      "product_name": "u3032rg accolade hoodie charcoal mens",
      "category": "outerwear",
      "subcategory": "hoodies",
      "gender": "mens",
      "first_seen": "2026-02-05T05:12:42.624159",
      "removed_at": "2026-02-12T02:05:04.631257",
      "returned_at": "2026-02-12T06:08:22.622881",
      "days_gone": 0
    },
    {
      "brand": "alo",
      "url": "https://www.aloyoga.com/products/w6435r-airlift-down-the-line-tennis-skirt-burgundy-truffle",
      "product_name": "w6435r airlift down the line tennis skirt truffle",
      "category": "bottoms",
      "subcategory": "skirts",
      "gender": "womens",
      "first_seen": "2026-02-05T11:50:28.076288",
      "removed_at": "2026-02-12T02:05:04.631257",
      "returned_at": "2026-02-12T06:08:22.622881",
      "days_gone": 0
    },
    {
      "brand": "alo",
      "url": "https://www.aloyoga.com/products/w3924rg-cropped-accolade-crewneck-celestial-blue",
      "product_name": "w3924rg cropped accolade crewneck celestial",
      "category": "tops",
      "subcategory": "crop_tops",
      "gender": "unisex",
      "first_seen": "2026-02-05T11:50:28.076580",
      "removed_at": "2026-02-12T02:05:04.631257",
      "returned_at": "2026-02-12T06:08:22.622881",
      "days_gone": 0
    },
    {
      "brand": "alo",
      "url": "https://www.aloyoga.com/products/a0543u-performance-off-duty-cap-lunar-grey",
      "product_name": "a0543u performance off duty cap lunar",
      "category": "accessories",
      "subcategory": "hats",
      "gender": "unisex",
      "first_seen": "2026-02-05T11:50:28.080864",
      "removed_at": "2026-02-12T02:05:04.631257",
      "returned_at": "2026-02-12T06:08:22.622881",
      "days_gone": 0
    },
    {
      "brand": "alo",
      "url": "https://www.aloyoga.com/products/w4703r-track-star-full-zip-jacket-burgundy",
      "product_name": "w4703r track star full zip jacket",
      "category": "outerwear",
      "subcategory": "jackets",
      "gender": "womens",
      "first_seen": "2026-02-05T11:50:28.081908",
      "removed_at": "2026-02-12T02:05:04.631257",
      "returned_at": "2026-02-12T06:08:22.622881",
      "days_gone": 0
    },
    {
      "brand": "alo",
      "url": "https://www.aloyoga.com/products/u3031rg-accolade-crew-neck-pullover-pink-wild-rose",
      "product_name": "u3031rg accolade crew neck pullover pink wild",
      "category": "outerwear",
      "subcategory": "pullovers",
      "gender": "unisex",
      "first_seen": "2026-02-05T19:52:57.857534",
      "removed_at": "2026-02-12T02:05:04.631257",
      "returned_at": "2026-02-12T06:08:22.622881",
      "days_gone": 0
    },
    {
      "brand": "alo",
      "url": "https://www.aloyoga.com/products/w54260r-pinstripe-daylight-boxer-pant-regular-black-titanium",
      "product_name": "w54260r pinstripe daylight boxer pant regular titanium",
      "category": "bottoms",
      "subcategory": "pants",
      "gender": "mens",
      "first_seen": "2026-02-05T19:52:57.858078",
      "removed_at": "2026-02-12T02:05:04.631257",
      "returned_at": "2026-02-12T06:08:22.622881",
      "days_gone": 0
    },
    {
      "brand": "alo",
      "url": "https://www.aloyoga.com/products/u3031rg-accolade-crew-neck-pullover-pink-wild-rose-mens",
      "product_name": "u3031rg accolade crew neck pullover pink wild mens",
      "category": "outerwear",
      "subcategory": "pullovers",
      "gender": "mens",
      "first_seen": "2026-02-05T19:52:57.858558",
      "removed_at": "2026-02-12T02:05:04.631257",
      "returned_at": "2026-02-12T06:08:22.622881",
      "days_gone": 0
    },
    {
      "brand": "gymshark",
      "url": "https://www.gymshark.com/products/gymshark-essential-oversized-t-shirt-charcoal-grey-marl-ss23",
      "product_name": "gymshark essential oversized t shirt charcoal",
      "category": "tops",
      "subcategory": "other",
      "gender": "unisex",
      "first_seen": "2026-02-03T23:12:37.136379",
      "removed_at": "2026-02-12T02:05:04.631257",
      "returned_at": "2026-02-12T06:08:22.622881",
      "days_gone": 0
    },
    {
      "brand": "gymshark",
      "url": "https://www.gymshark.com/products/gymshark-crew-socks-3pk-white-light-grey-core-marl-black-ss23",
      "product_name": "gymshark crew socks 3pk white light grey core",
      "category": "accessories",
      "subcategory": "socks",
      "gender": "unisex",
      "first_seen": "2026-02-03T23:12:37.137105",
      "removed_at": "2026-02-12T02:05:04.631257",
      "returned_at": "2026-02-12T06:08:22.622881",
      "days_gone": 0
    },
    {
      "brand": "gymshark",
      "url": "https://www.gymshark.com/products/gymshark-worn-graphic-hoodie-pullovers-grey-aw25",
      "product_name": "gymshark worn graphic hoodie pullovers",
      "category": "outerwear",
      "subcategory": "hoodies",
      "gender": "unisex",
      "first_seen": "2026-02-03T23:12:37.141878",
      "removed_at": "2026-02-12T02:05:04.631257",
      "returned_at": "2026-02-12T06:08:22.622881",
      "days_gone": 0
    },
    {
      "brand": "gymshark",
      "url": "https://www.gymshark.com/es-US/products/gymshark-essential-oversized-t-shirt-charcoal-grey-marl-ss23",
      "product_name": "gymshark essential oversized t shirt charcoal",
      "category": "tops",
      "subcategory": "other",
      "gender": "unisex",
      "first_seen": "2026-02-03T23:12:37.155472",
      "removed_at": "2026-02-12T02:05:04.631257",
      "returned_at": "2026-02-12T06:08:22.622881",
      "days_gone": 0
    },
    {
      "brand": "gymshark",
      "url": "https://www.gymshark.com/es-US/products/gymshark-crew-socks-3pk-white-light-grey-core-marl-black-ss23",
      "product_name": "gymshark crew socks 3pk white light grey core",
      "category": "accessories",
      "subcategory": "socks",
      "gender": "unisex",
      "first_seen": "2026-02-03T23:12:37.156187",
      "removed_at": "2026-02-12T02:05:04.631257",
      "returned_at": "2026-02-12T06:08:22.622881",
      "days_gone": 0
    },
    {
      "brand": "gymshark",
      "url": "https://www.gymshark.com/es-US/products/gymshark-worn-graphic-hoodie-pullovers-grey-aw25",
      "product_name": "gymshark worn graphic hoodie pullovers",
      "category": "outerwear",
      "subcategory": "hoodies",
      "gender": "unisex",
      "first_seen": "2026-02-03T23:12:37.161316",
      "removed_at": "2026-02-12T02:05:04.631257",
      "returned_at": "2026-02-12T06:08:22.622881",
      "days_gone": 0
    },
    {
      "brand": "gymshark",
      "url": "https://www.gymshark.com/products/gymshark-outline-graphic-long-sleeve-baselayer-ls-tops-black-aw25",
      "product_name": "gymshark outline graphic long sleeve baselayer ls tops",
      "category": "other",
      "subcategory": "other",
      "gender": "unisex",
      "first_seen": "2026-02-05T11:50:33.019832",
      "removed_at": "2026-02-12T02:05:04.631257",
      "returned_at": "2026-02-12T06:08:22.622881",
      "days_gone": 0
    },
    {
      "brand": "gymshark",
      "url": "https://www.gymshark.com/products/gymshark-everyday-seamless-racerback-sports-bra-sports-bras-green-aw25",
      "product_name": "gymshark everyday seamless racerback sports bra sports bras",
      "category": "sports_bras",
      "subcategory": "other",
      "gender": "womens",
      "first_seen": "2026-02-05T11:50:33.020114",
      "removed_at": "2026-02-12T02:05:04.631257",
      "returned_at": "2026-02-12T06:08:22.622881",
      "days_gone": 0
    },
    {
      "brand": "gymshark",
      "url": "https://www.gymshark.com/es-US/products/gymshark-outline-graphic-long-sleeve-baselayer-ls-tops-black-aw25",
      "product_name": "gymshark outline graphic long sleeve baselayer ls tops",
      "category": "other",
      "subcategory": "other",
      "gender": "unisex",
      "first_seen": "2026-02-05T11:50:33.026654",
      "removed_at": "2026-02-12T02:05:04.631257",
      "returned_at": "2026-02-12T06:08:22.622881",
      "days_gone": 0
    },
    {
      "brand": "gymshark",
      "url": "https://www.gymshark.com/es-US/products/gymshark-everyday-seamless-racerback-sports-bra-sports-bras-green-aw25",
      "product_name": "gymshark everyday seamless racerback sports bra sports bras",
      "category": "sports_bras",
      "subcategory": "other",
      "gender": "womens",
      "first_seen": "2026-02-05T11:50:33.026935",
      "removed_at": "2026-02-12T02:05:04.631257",
      "returned_at": "2026-02-12T06:08:22.622881",
      "days_gone": 0
    },
    {
      "brand": "gymshark",
      "url": "https://www.gymshark.com/products/power-short-leggings-black-ss24",
      "product_name": "power short leggings",
      "category": "bottoms",
      "subcategory": "leggings",
      "gender": "womens",
      "first_seen": "2026-02-05T15:51:36.963668",
      "removed_at": "2026-02-12T02:05:04.631257",
      "returned_at": "2026-02-12T06:08:22.622881",
      "days_gone": 0
    },
    {
      "brand": "gymshark",
      "url": "https://www.gymshark.com/products/gymshark-studio-joggers-black-aw24",
      "product_name": "gymshark studio joggers",
      "category": "bottoms",
      "subcategory": "joggers",
      "gender": "mens",
      "first_seen": "2026-02-05T15:51:36.963974",
      "removed_at": "2026-02-12T02:05:04.631257",
      "returned_at": "2026-02-12T06:08:22.622881",
      "days_gone": 0
    },
    {
      "brand": "gymshark",
      "url": "https://www.gymshark.com/es-US/products/power-short-leggings-black-ss24",
      "product_name": "power short leggings",
      "category": "bottoms",
      "subcategory": "leggings",
      "gender": "womens",
      "first_seen": "2026-02-05T15:51:36.971124",
      "removed_at": "2026-02-12T02:05:04.631257",
      "returned_at": "2026-02-12T06:08:22.622881",
      "days_gone": 0
    },
    {
      "brand": "gymshark",
      "url": "https://www.gymshark.com/es-US/products/gymshark-studio-joggers-black-aw24",
      "product_name": "gymshark studio joggers",
      "category": "bottoms",
      "subcategory": "joggers",
      "gender": "mens",
      "first_seen": "2026-02-05T15:51:36.971432",
      "removed_at": "2026-02-12T02:05:04.631257",
      "returned_at": "2026-02-12T06:08:22.622881",
      "days_gone": 0
    },
    {
      "brand": "gymshark",
      "url": "https://www.gymshark.com/products/gymshark-vital-seamless-2-0-crop-top-functional-purple-marl-ss25",
      "product_name": "gymshark vital seamless 2 0 crop top functional",
      "category": "tops",
      "subcategory": "crop_tops",
      "gender": "womens",
      "first_seen": "2026-02-05T19:53:04.443266",
      "removed_at": "2026-02-12T02:05:04.631257",
      "returned_at": "2026-02-12T06:08:22.622881",
      "days_gone": 0
    },
    {
      "brand": "gymshark",
      "url": "https://www.gymshark.com/es-US/products/gymshark-vital-seamless-2-0-crop-top-functional-purple-marl-ss25",
      "product_name": "gymshark vital seamless 2 0 crop top functional",
      "category": "tops",
      "subcategory": "crop_tops",
      "gender": "womens",
      "first_seen": "2026-02-05T19:53:04.450538",
      "removed_at": "2026-02-12T02:05:04.631257",
      "returned_at": "2026-02-12T06:08:22.622881",
      "days_gone": 0
    },
    {
      "brand": "gymshark",
      "url": "https://www.gymshark.com/es-US/products/gymshark-everyday-seamless-contrast-legging-leggings-1",
      "product_name": "gymshark everyday seamless contrast legging leggings",
      "category": "bottoms",
      "subcategory": "leggings",
      "gender": "womens",
      "first_seen": "2026-02-06T20:00:43.029083",
      "removed_at": "2026-02-12T02:05:04.631257",
      "returned_at": "2026-02-12T06:08:22.622881",
      "days_gone": 0
    },
    {
      "brand": "gymshark",
      "url": "https://www.gymshark.com/products/gymshark-everyday-seamless-contrast-legging-leggings-1",
      "product_name": "gymshark everyday seamless contrast legging leggings",
      "category": "bottoms",
      "subcategory": "leggings",
      "gender": "womens",
      "first_seen": "2026-02-06T20:03:40.472781",
      "removed_at": "2026-02-12T02:05:04.631257",
      "returned_at": "2026-02-12T06:08:22.622881",
      "days_gone": 0
    },
    {
      "brand": "gymshark",
      "url": "https://www.gymshark.com/products/gymshark-everyday-seamless-sports-bra-soft-white-ss25",
      "product_name": "gymshark everyday seamless sports bra",
      "category": "sports_bras",
      "subcategory": "other",
      "gender": "womens",
      "first_seen": "2026-02-09T12:00:52.526405",
      "removed_at": "2026-02-12T02:05:04.631257",
      "returned_at": "2026-02-12T06:08:22.622881",
      "days_gone": 0
    },
    {
      "brand": "gymshark",
      "url": "https://www.gymshark.com/products/gymshark-arrival-block-track-jacket-jackets-outerwear-black-aw25",
      "product_name": "gymshark arrival block track jacket jackets outerwear",
      "category": "outerwear",
      "subcategory": "jackets",
      "gender": "mens",
      "first_seen": "2026-02-09T12:00:52.527944",
      "removed_at": "2026-02-12T02:05:04.631257",
      "returned_at": "2026-02-12T06:08:22.622881",
      "days_gone": 0
    },
    {
      "brand": "gymshark",
      "url": "https://www.gymshark.com/products/gymshark-essential-oversized-t-shirt-ss-tops-blue-aw25",
      "product_name": "gymshark essential oversized t shirt ss tops",
      "category": "tops",
      "subcategory": "other",
      "gender": "unisex",
      "first_seen": "2026-02-09T12:00:52.528472",
      "removed_at": "2026-02-12T02:05:04.631257",
      "returned_at": "2026-02-12T06:08:22.622881",
      "days_gone": 0
    },
    {
      "brand": "gymshark",
      "url": "https://www.gymshark.com/products/gymshark-power-t-shirt-ss-tops-blue-aw25-2",
      "product_name": "gymshark power t shirt ss tops aw25",
      "category": "tops",
      "subcategory": "other",
      "gender": "mens",
      "first_seen": "2026-02-09T12:00:52.530080",
      "removed_at": "2026-02-12T02:05:04.631257",
      "returned_at": "2026-02-12T06:08:22.622881",
      "days_gone": 0
    },
    {
      "brand": "gymshark",
      "url": "https://www.gymshark.com/es-US/products/gymshark-everyday-seamless-sports-bra-soft-white-ss25",
      "product_name": "gymshark everyday seamless sports bra",
      "category": "sports_bras",
      "subcategory": "other",
      "gender": "womens",
      "first_seen": "2026-02-09T12:00:52.533261",
      "removed_at": "2026-02-12T02:05:04.631257",
      "returned_at": "2026-02-12T06:08:22.622881",
      "days_gone": 0
    },
    {
      "brand": "gymshark",
      "url": "https://www.gymshark.com/es-US/products/gymshark-arrival-block-track-jacket-jackets-outerwear-black-aw25",
      "product_name": "gymshark arrival block track jacket jackets outerwear",
      "category": "outerwear",
      "subcategory": "jackets",
      "gender": "mens",
      "first_seen": "2026-02-09T12:00:52.534810",
      "removed_at": "2026-02-12T02:05:04.631257",
      "returned_at": "2026-02-12T06:08:22.622881",
      "days_gone": 0
    },
    {
      "brand": "gymshark",
      "url": "https://www.gymshark.com/es-US/products/gymshark-essential-oversized-t-shirt-ss-tops-blue-aw25",
      "product_name": "gymshark essential oversized t shirt ss tops",
      "category": "tops",
      "subcategory": "other",
      "gender": "unisex",
      "first_seen": "2026-02-09T12:00:52.535336",
      "removed_at": "2026-02-12T02:05:04.631257",
      "returned_at": "2026-02-12T06:08:22.622881",
      "days_gone": 0
    },
    {
      "brand": "gymshark",
      "url": "https://www.gymshark.com/es-US/products/gymshark-power-t-shirt-ss-tops-blue-aw25-2",
      "product_name": "gymshark power t shirt ss tops aw25",
      "category": "tops",
      "subcategory": "other",
      "gender": "mens",
      "first_seen": "2026-02-09T12:00:52.536899",
      "removed_at": "2026-02-12T02:05:04.631257",
      "returned_at": "2026-02-12T06:08:22.622881",
      "days_gone": 0
    },
    {
      "brand": "gymshark",
      "url": "https://www.gymshark.com/products/gymshark-power-long-sleeve-t-shirt-ls-tops-black-aw25-2",
      "product_name": "gymshark power long sleeve t shirt ls tops aw25",
      "category": "tops",
      "subcategory": "long_sleeve",
      "gender": "mens",
      "first_seen": "2026-02-09T16:00:52.443899",
      "removed_at": "2026-02-12T02:05:04.631257",
      "returned_at": "2026-02-12T06:08:22.622881",
      "days_gone": 0
    },
    {
      "brand": "gymshark",
      "url": "https://www.gymshark.com/es-US/products/gymshark-power-long-sleeve-t-shirt-ls-tops-black-aw25-2",
      "product_name": "gymshark power long sleeve t shirt ls tops aw25",
      "category": "tops",
      "subcategory": "long_sleeve",
      "gender": "mens",
      "first_seen": "2026-02-09T16:00:52.451240",
      "removed_at": "2026-02-12T02:05:04.631257",
      "returned_at": "2026-02-12T06:08:22.622881",
      "days_gone": 0
    },
    {
      "brand": "gymshark",
      "url": "https://www.gymshark.com/products/gymshark-lifting-essentials-graphic-brushed-oversized-joggers-black-ss25",
      "product_name": "gymshark lifting essentials graphic brushed oversized joggers",
      "category": "bottoms",
      "subcategory": "joggers",
      "gender": "mens",
      "first_seen": "2026-02-09T16:10:55.172309",
      "removed_at": "2026-02-12T02:05:04.631257",
      "returned_at": "2026-02-12T06:08:22.622881",
      "days_gone": 0
    },
    {
      "brand": "gymshark",
      "url": "https://www.gymshark.com/products/gymshark-power-long-sleeve-t-shirt-ls-tops-grey-aw25-2",
      "product_name": "gymshark power long sleeve t shirt ls tops aw25",
      "category": "tops",
      "subcategory": "long_sleeve",
      "gender": "mens",
      "first_seen": "2026-02-10T09:11:53.776110",
      "removed_at": "2026-02-12T02:05:04.631257",
      "returned_at": "2026-02-12T06:08:22.622881",
      "days_gone": 0
    },
    {
      "brand": "gymshark",
      "url": "https://www.gymshark.com/products/gymshark-all-seasons-graphic-short-sleeve-t-shirt-ss-tops",
      "product_name": "gymshark all seasons graphic short sleeve t shirt ss tops",
      "category": "bottoms",
      "subcategory": "other",
      "gender": "unisex",
      "first_seen": "2026-02-10T09:11:53.776605",
      "removed_at": "2026-02-12T02:05:04.631257",
      "returned_at": "2026-02-12T06:08:22.622881",
      "days_gone": 0
    },
    {
      "brand": "gymshark",
      "url": "https://www.gymshark.com/es-US/products/gymshark-power-long-sleeve-t-shirt-ls-tops-grey-aw25-2",
      "product_name": "gymshark power long sleeve t shirt ls tops aw25",
      "category": "tops",
      "subcategory": "long_sleeve",
      "gender": "mens",
      "first_seen": "2026-02-10T09:13:07.092000",
      "removed_at": "2026-02-12T02:05:04.631257",
      "returned_at": "2026-02-12T06:08:22.622881",
      "days_gone": 0
    },
    {
      "brand": "gymshark",
      "url": "https://www.gymshark.com/es-US/products/gymshark-lifting-essentials-graphic-brushed-oversized-joggers-black-ss25",
      "product_name": "gymshark lifting essentials graphic brushed oversized joggers",
      "category": "bottoms",
      "subcategory": "joggers",
      "gender": "mens",
      "first_seen": "2026-02-10T12:03:54.714935",
      "removed_at": "2026-02-12T02:05:04.631257",
      "returned_at": "2026-02-12T06:08:22.622881",
      "days_gone": 0
    },
    {
      "brand": "gymshark",
      "url": "https://www.gymshark.com/es-US/products/gymshark-all-seasons-graphic-short-sleeve-t-shirt-ss-tops",
      "product_name": "gymshark all seasons graphic short sleeve t shirt ss tops",
      "category": "bottoms",
      "subcategory": "other",
      "gender": "unisex",
      "first_seen": "2026-02-10T13:13:22.728432",
      "removed_at": "2026-02-12T02:05:04.631257",
      "returned_at": "2026-02-12T06:08:22.622881",
      "days_gone": 0
    }
  ],
  "summary": {
    "total": 124,
    "by_brand": {
      "vuori": 58,
      "alo": 32,
      "gymshark": 34
    },
    "avg_days_gone": 0.0
  },
  "generated_at": "2026-02-12T06:08:41.293130"
}